.gitignore
CHANGES.txt
CONTRIBUTORS.txt
MANIFEST.in
README.rst
setup.py
docs/LICENSE.GPL
docs/LICENSE.txt
docs/MANUAL.txt
src/raptus/__init__.py
src/raptus.article.accordion.egg-info/PKG-INFO
src/raptus.article.accordion.egg-info/SOURCES.txt
src/raptus.article.accordion.egg-info/dependency_links.txt
src/raptus.article.accordion.egg-info/entry_points.txt
src/raptus.article.accordion.egg-info/namespace_packages.txt
src/raptus.article.accordion.egg-info/not-zip-safe
src/raptus.article.accordion.egg-info/requires.txt
src/raptus.article.accordion.egg-info/top_level.txt
src/raptus/article/__init__.py
src/raptus/article/accordion/__init__.py
src/raptus/article/accordion/configure.zcml
src/raptus/article/accordion/browser/__init__.py
src/raptus/article/accordion/browser/accordion.gif
src/raptus/article/accordion/browser/accordion.js
src/raptus/article/accordion/browser/accordion.py
src/raptus/article/accordion/browser/configure.zcml
src/raptus/article/accordion/i18n/raptus.article-de.mo
src/raptus/article/accordion/i18n/raptus.article-de.po
src/raptus/article/accordion/i18n/raptus.article.pot
src/raptus/article/accordion/profiles/default/cssregistry.xml
src/raptus/article/accordion/profiles/default/jsregistry.xml
src/raptus/article/accordion/profiles/default/metadata.xml
src/raptus/article/accordion/profiles/default/propertiestool.xml
src/raptus/article/accordion/profiles/default/skins.xml
src/raptus/article/accordion/profiles/default/viewlets.xml
src/raptus/article/accordion/skins/raptus_article_accordion/raptus.article.accordion.css.dtml