Metadata-Version: 1.1
Name: raptus.article.accordion
Version: 1.0a1
Summary: Provides an article listing displayed as an accordion
Home-page: http://github.com/Raptus/raptus.article.accordion
Author: Raptus AG
Author-email: dev@raptus.com
License: gpl
Platform: UNKNOWN
Classifier: Programming Language :: Python
